{
  "openapi": "3.0.4",
  "info": {
    "title": "BattleShipApi",
    "version": "1.0"
  },
  "paths": {
    "/api/BattleShip": {
      "get": {
        "tags": [
          "BattleShip"
        ],
        "responses": {
          "200": {
            "description": "OK",
            "content": {
              "text/plain": {
                "schema": {
                  "type": "array",
                  "items": {
                    "type": "string"
                  }
                }
              },
              "application/json": {
                "schema": {
                  "type": "array",
                  "items": {
                    "type": "string"
                  }
                }
              },
              "text/json": {
                "schema": {
                  "type": "array",
                  "items": {
                    "type": "string"
                  }
                }
              }
            }
          }
        }
      },
      "post": {
        "tags": [
          "BattleShip"
        ],
        "requestBody": {
          "content": {
            "application/json": {
              "schema": {
                "type": "string"
              }
            },
            "text/json": {
              "schema": {
                "type": "string"
              }
            },
            "application/*+json": {
              "schema": {
                "type": "string"
              }
            }
          }
        },
        "responses": {
          "200": {
            "description": "OK"
          }
        }
      }
    },
    "/api/BattleShip/{id}": {
      "get": {
        "tags": [
          "BattleShip"
        ],
        "parameters": [
          {
            "name": "id",
            "in": "path",
            "required": true,
            "schema": {
              "type": "integer",
              "format": "int32"
            }
          }
        ],
        "responses": {
          "200": {
            "description": "OK",
            "content": {
              "text/plain": {
                "schema": {
                  "type": "string"
                }
              },
              "application/json": {
                "schema": {
                  "type": "string"
                }
              },
              "text/json": {
                "schema": {
                  "type": "string"
                }
              }
            }
          }
        }
      },
      "put": {
        "tags": [
          "BattleShip"
        ],
        "parameters": [
          {
            "name": "id",
            "in": "path",
            "required": true,
            "schema": {
              "type": "integer",
              "format": "int32"
            }
          }
        ],
        "requestBody": {
          "content": {
            "application/json": {
              "schema": {
                "type": "string"
              }
            },
            "text/json": {
              "schema": {
                "type": "string"
              }
            },
            "application/*+json": {
              "schema": {
                "type": "string"
              }
            }
          }
        },
        "responses": {
          "200": {
            "description": "OK"
          }
        }
      },
      "delete": {
        "tags": [
          "BattleShip"
        ],
        "parameters": [
          {
            "name": "id",
            "in": "path",
            "required": true,
            "schema": {
              "type": "integer",
              "format": "int32"
            }
          }
        ],
        "responses": {
          "200": {
            "description": "OK"
          }
        }
      }
    },
    "/": {
      "get": {
        "tags": [
          "BattleShipApi"
        ],
        "responses": {
          "200": {
            "description": "OK",
            "content": {
              "text/plain": {
                "schema": {
                  "type": "string"
                }
              }
            }
          }
        }
      }
    },
    "/api/Match": {
      "post": {
        "tags": [
          "Match"
        ],
        "responses": {
          "200": {
            "description": "OK",
            "content": {
              "text/plain": {
                "schema": {
                  "$ref": "#/components/schemas/CreateMatchResponse"
                }
              },
              "application/json": {
                "schema": {
                  "$ref": "#/components/schemas/CreateMatchResponse"
                }
              },
              "text/json": {
                "schema": {
                  "$ref": "#/components/schemas/CreateMatchResponse"
                }
              }
            }
          }
        }
      }
    },
    "/api/Match/join": {
      "post": {
        "tags": [
          "Match"
        ],
        "requestBody": {
          "content": {
            "application/json": {
              "schema": {
                "$ref": "#/components/schemas/JoinMatchRequest"
              }
            },
            "text/json": {
              "schema": {
                "$ref": "#/components/schemas/JoinMatchRequest"
              }
            },
            "application/*+json": {
              "schema": {
                "$ref": "#/components/schemas/JoinMatchRequest"
              }
            }
          }
        },
        "responses": {
          "200": {
            "description": "OK",
            "content": {
              "text/plain": {
                "schema": {
                  "$ref": "#/components/schemas/JoinMatchResponse"
                }
              },
              "application/json": {
                "schema": {
                  "$ref": "#/components/schemas/JoinMatchResponse"
                }
              },
              "text/json": {
                "schema": {
                  "$ref": "#/components/schemas/JoinMatchResponse"
                }
              }
            }
          }
        }
      }
    }
  },
  "components": {
    "schemas": {
      "CreateMatchResponse": {
        "type": "object",
        "properties": {
          "matchId": {
            "type": "string",
            "format": "uuid"
          },
          "matchCode": {
            "type": "integer",
            "format": "int32"
          }
        },
        "additionalProperties": false
      },
      "JoinMatchRequest": {
        "type": "object",
        "properties": {
          "matchCode": {
            "type": "integer",
            "format": "int32"
          },
          "playerName": {
            "type": "string",
            "nullable": true
          }
        },
        "additionalProperties": false
      },
      "JoinMatchResponse": {
        "type": "object",
        "properties": {
          "matchId": {
            "type": "string",
            "format": "uuid"
          },
          "playerId": {
            "type": "string",
            "format": "uuid"
          },
          "playerName": {
            "type": "string",
            "nullable": true
          },
          "playerNumber": {
            "type": "integer",
            "format": "int32"
          }
        },
        "additionalProperties": false
      }
    }
  },
  "tags": [
    {
      "name": "BattleShip"
    },
    {
      "name": "BattleShipApi"
    },
    {
      "name": "Match"
    }
  ]
}